[
  {
    "goodsId": "506001",
    "goodsName": "日神卡",
    "totalSkus": 0,
    "totalCombos": 0,
    "variants": []
  },
  {
    "goodsId": "900778",
    "goodsName": "澳門上網卡",
    "totalSkus": 5,
    "totalCombos": 5,
    "variants": [
      {
        "prepaidCardId": 900701,
        "realPrice": 18,
        "oriPrice": 28,
        "stockNum": 910,
        "dayOptions": [
          "1"
        ],
        "dataOptions": [
          "103"
        ]
      },
      {
        "prepaidCardId": 900702,
        "realPrice": 23,
        "oriPrice": 38,
        "stockNum": 282,
        "dayOptions": [
          "2"
        ],
        "dataOptions": [
          "103"
        ]
      },
      {
        "prepaidCardId": 900703,
        "realPrice": 27,
        "oriPrice": 48,
        "stockNum": 360,
        "dayOptions": [
          "3"
        ],
        "dataOptions": [
          "103"
        ]
      },
      {
        "prepaidCardId": 900704,
        "realPrice": 30,
        "oriPrice": 68,
        "stockNum": 448,
        "dayOptions": [
          "5"
        ],
        "dataOptions": [
          "103"
        ]
      },
      {
        "prepaidCardId": 900705,
        "realPrice": 33,
        "oriPrice": 78,
        "stockNum": 485,
        "dayOptions": [
          "7"
        ],
        "dataOptions": [
          "103"
        ]
      }
    ]
  },
  {
    "goodsId": "1021002",
    "goodsName": "香港多日上網卡",
    "totalSkus": 1,
    "totalCombos": 4,
    "variants": [
      {
        "prepaidCardId": 11237874,
        "realPrice": 20,
        "oriPrice": 49,
        "stockNum": 212,
        "dayOptions": [
          "3",
          "30",
          "365",
          "7"
        ],
        "dataOptions": [
          "6"
        ]
      }
    ]
  },
  {
    "goodsId": "1021004",
    "goodsName": "香港及澳門多日上網卡",
    "totalSkus": 2,
    "totalCombos": 4,
    "variants": [
      {
        "prepaidCardId": 11237879,
        "realPrice": 25,
        "oriPrice": 66,
        "stockNum": 285,
        "dayOptions": [
          "4"
        ],
        "dataOptions": [
          "102048"
        ]
      },
      {
        "prepaidCardId": 11237881,
        "realPrice": 32,
        "oriPrice": 86,
        "stockNum": 284,
        "dayOptions": [
          "180",
          "7",
          "8"
        ],
        "dataOptions": [
          "102048"
        ]
      }
    ]
  },
  {
    "goodsId": "1021006",
    "goodsName": "中國內地及澳門多日上網卡",
    "totalSkus": 5,
    "totalCombos": 40,
    "variants": [
      {
        "prepaidCardId": 11238603,
        "realPrice": 483,
        "oriPrice": 768,
        "stockNum": 962,
        "dayOptions": [
          "90"
        ],
        "dataOptions": [
          "102400",
          "330005",
          "50"
        ]
      },
      {
        "prepaidCardId": 11237174,
        "realPrice": 116,
        "oriPrice": 280,
        "stockNum": 1025,
        "dayOptions": [
          "180"
        ],
        "dataOptions": [
          "21+3"
        ]
      },
      {
        "prepaidCardId": 11238599,
        "realPrice": 508,
        "oriPrice": 898,
        "stockNum": 968,
        "dayOptions": [
          "11",
          "15",
          "180",
          "2",
          "3",
          "30",
          "5",
          "8",
          "90"
        ],
        "dataOptions": [
          "102400",
          "21+3",
          "330005",
          "50"
        ]
      },
      {
        "prepaidCardId": 11237151,
        "realPrice": 207,
        "oriPrice": 398,
        "stockNum": 1348,
        "dayOptions": [
          "180"
        ],
        "dataOptions": [
          "330005"
        ]
      },
      {
        "prepaidCardId": 10237025,
        "realPrice": 386,
        "oriPrice": 698,
        "stockNum": 1257,
        "dayOptions": [
          "180",
          "365"
        ],
        "dataOptions": [
          "102400",
          "21+3",
          "330005",
          "50"
        ]
      }
    ]
  },
  {
    "goodsId": "1021010",
    "goodsName": "日本多日通話/上網卡",
    "totalSkus": 2,
    "totalCombos": 6,
    "variants": [
      {
        "prepaidCardId": 11237874,
        "realPrice": 20,
        "oriPrice": 49,
        "stockNum": 212,
        "dayOptions": [
          "3"
        ],
        "dataOptions": [
          "5+3"
        ]
      },
      {
        "prepaidCardId": 11237157,
        "realPrice": 64,
        "oriPrice": 108,
        "stockNum": 500,
        "dayOptions": [
          "10",
          "15",
          "30",
          "5",
          "8"
        ],
        "dataOptions": [
          "5+3"
        ]
      }
    ]
  },
  {
    "goodsId": "1021011",
    "goodsName": "南韓多日通話/上網卡",
    "totalSkus": 6,
    "totalCombos": 10,
    "variants": [
      {
        "prepaidCardId": 10237004,
        "realPrice": 47,
        "oriPrice": 118,
        "stockNum": 925,
        "dayOptions": [
          "3"
        ],
        "dataOptions": [
          "10"
        ]
      },
      {
        "prepaidCardId": 11237675,
        "realPrice": 27,
        "oriPrice": 78,
        "stockNum": 997,
        "dayOptions": [
          "3"
        ],
        "dataOptions": [
          "103072"
        ]
      },
      {
        "prepaidCardId": 10237006,
        "realPrice": 43,
        "oriPrice": 128,
        "stockNum": 979,
        "dayOptions": [
          "5"
        ],
        "dataOptions": [
          "10"
        ]
      },
      {
        "prepaidCardId": 11237677,
        "realPrice": 40,
        "oriPrice": 108,
        "stockNum": 983,
        "dayOptions": [
          "5",
          "8"
        ],
        "dataOptions": [
          "10",
          "103072"
        ]
      },
      {
        "prepaidCardId": 11237679,
        "realPrice": 53,
        "oriPrice": 178,
        "stockNum": 987,
        "dayOptions": [
          "15",
          "8"
        ],
        "dataOptions": [
          "10",
          "103072"
        ]
      },
      {
        "prepaidCardId": 11237681,
        "realPrice": 94,
        "oriPrice": 238,
        "stockNum": 1000,
        "dayOptions": [
          "15",
          "30"
        ],
        "dataOptions": [
          "10",
          "103072"
        ]
      }
    ]
  },
  {
    "goodsId": "1021012",
    "goodsName": "日韓多日通話/上網卡",
    "totalSkus": 1,
    "totalCombos": 2,
    "variants": [
      {
        "prepaidCardId": 10237004,
        "realPrice": 47,
        "oriPrice": 118,
        "stockNum": 925,
        "dayOptions": [
          "15",
          "6"
        ],
        "dataOptions": [
          "103072"
        ]
      }
    ]
  },
  {
    "goodsId": "1021013",
    "goodsName": "越南多日通話/上網卡",
    "totalSkus": 5,
    "totalCombos": 6,
    "variants": [
      {
        "prepaidCardId": 11237801,
        "realPrice": 18,
        "oriPrice": 38,
        "stockNum": 966,
        "dayOptions": [
          "2"
        ],
        "dataOptions": [
          "102048"
        ]
      },
      {
        "prepaidCardId": 11237802,
        "realPrice": 21,
        "oriPrice": 48,
        "stockNum": 895,
        "dayOptions": [
          "3"
        ],
        "dataOptions": [
          "102048"
        ]
      },
      {
        "prepaidCardId": 11237803,
        "realPrice": 29,
        "oriPrice": 78,
        "stockNum": 114,
        "dayOptions": [
          "5"
        ],
        "dataOptions": [
          "102048"
        ]
      },
      {
        "prepaidCardId": 11237804,
        "realPrice": 34,
        "oriPrice": 98,
        "stockNum": 583,
        "dayOptions": [
          "7",
          "8"
        ],
        "dataOptions": [
          "102048"
        ]
      },
      {
        "prepaidCardId": 11237805,
        "realPrice": 57,
        "oriPrice": 188,
        "stockNum": 884,
        "dayOptions": [
          "15"
        ],
        "dataOptions": [
          "102048"
        ]
      }
    ]
  },
  {
    "goodsId": "1021014",
    "goodsName": "泰國多日上網卡",
    "totalSkus": 1,
    "totalCombos": 5,
    "variants": [
      {
        "prepaidCardId": 11238516,
        "realPrice": 25,
        "oriPrice": 58,
        "stockNum": 980,
        "dayOptions": [
          "15",
          "30",
          "5",
          "7",
          "8"
        ],
        "dataOptions": [
          "5120"
        ]
      }
    ]
  },
  {
    "goodsId": "1021016",
    "goodsName": "星馬泰及印尼多日通話/上網卡",
    "totalSkus": 3,
    "totalCombos": 3,
    "variants": [
      {
        "prepaidCardId": 11239663,
        "realPrice": 36,
        "oriPrice": 118,
        "stockNum": 272,
        "dayOptions": [
          "5"
        ],
        "dataOptions": [
          "103072"
        ]
      },
      {
        "prepaidCardId": 11237166,
        "realPrice": 44,
        "oriPrice": 188,
        "stockNum": 1608,
        "dayOptions": [
          "8"
        ],
        "dataOptions": [
          "103072"
        ]
      },
      {
        "prepaidCardId": 11237168,
        "realPrice": 76,
        "oriPrice": 208,
        "stockNum": 1090,
        "dayOptions": [
          "15"
        ],
        "dataOptions": [
          "103072"
        ]
      }
    ]
  },
  {
    "goodsId": "1021017",
    "goodsName": "東盟8日上網卡",
    "totalSkus": 1,
    "totalCombos": 1,
    "variants": [
      {
        "prepaidCardId": 10237020,
        "realPrice": 42,
        "oriPrice": 78,
        "stockNum": 254,
        "dayOptions": [
          "8"
        ],
        "dataOptions": [
          "4"
        ]
      }
    ]
  },
  {
    "goodsId": "1021018",
    "goodsName": "東南亞8日上網卡",
    "totalSkus": 1,
    "totalCombos": 1,
    "variants": [
      {
        "prepaidCardId": 10237021,
        "realPrice": 56,
        "oriPrice": 118,
        "stockNum": 432,
        "dayOptions": [
          "8"
        ],
        "dataOptions": [
          "5"
        ]
      }
    ]
  },
  {
    "goodsId": "1021019",
    "goodsName": "亞洲多日上網卡",
    "totalSkus": 1,
    "totalCombos": 3,
    "variants": [
      {
        "prepaidCardId": 10237022,
        "realPrice": 73,
        "oriPrice": 138,
        "stockNum": 199,
        "dayOptions": [
          "12",
          "30",
          "8"
        ],
        "dataOptions": [
          "5"
        ]
      }
    ]
  },
  {
    "goodsId": "1021023",
    "goodsName": "歐洲多日上網卡",
    "totalSkus": 1,
    "totalCombos": 3,
    "variants": [
      {
        "prepaidCardId": 11238608,
        "realPrice": 123,
        "oriPrice": 198,
        "stockNum": 987,
        "dayOptions": [
          "15",
          "30",
          "90"
        ],
        "dataOptions": [
          "8192"
        ]
      }
    ]
  },
  {
    "goodsId": "1021024",
    "goodsName": "澳紐多日通話/上網卡",
    "totalSkus": 3,
    "totalCombos": 8,
    "variants": [
      {
        "prepaidCardId": 11238608,
        "realPrice": 123,
        "oriPrice": 198,
        "stockNum": 987,
        "dayOptions": [
          "10",
          "15",
          "30"
        ],
        "dataOptions": [
          "102400",
          "51200"
        ]
      },
      {
        "prepaidCardId": 11238657,
        "realPrice": 373,
        "oriPrice": 800,
        "stockNum": 300,
        "dayOptions": [
          "90"
        ],
        "dataOptions": [
          "51200"
        ]
      },
      {
        "prepaidCardId": 11238659,
        "realPrice": 736,
        "oriPrice": 1200,
        "stockNum": 50,
        "dayOptions": [
          "90"
        ],
        "dataOptions": [
          "102400"
        ]
      }
    ]
  },
  {
    "goodsId": "1021030",
    "goodsName": "美加墨30日上網卡",
    "totalSkus": 2,
    "totalCombos": 2,
    "variants": [
      {
        "prepaidCardId": 11237384,
        "realPrice": 121,
        "oriPrice": 238,
        "stockNum": 281,
        "dayOptions": [
          "30"
        ],
        "dataOptions": [
          "12"
        ]
      },
      {
        "prepaidCardId": 10237036,
        "realPrice": 79,
        "oriPrice": 228,
        "stockNum": 383,
        "dayOptions": [
          "30"
        ],
        "dataOptions": [
          "10600"
        ]
      }
    ]
  },
  {
    "goodsId": "1021031",
    "goodsName": "阿聯酋30日上網卡",
    "totalSkus": 2,
    "totalCombos": 2,
    "variants": [
      {
        "prepaidCardId": 10237140,
        "realPrice": 63,
        "oriPrice": 268,
        "stockNum": 399,
        "dayOptions": [
          "30"
        ],
        "dataOptions": [
          "4"
        ]
      },
      {
        "prepaidCardId": 11237155,
        "realPrice": 89,
        "oriPrice": 278,
        "stockNum": 199,
        "dayOptions": [
          "30"
        ],
        "dataOptions": [
          "6"
        ]
      }
    ]
  },
  {
    "goodsId": "1021032",
    "goodsName": "沙特阿拉伯、埃及及土耳其30日上網卡",
    "totalSkus": 2,
    "totalCombos": 2,
    "variants": [
      {
        "prepaidCardId": 11237176,
        "realPrice": 96,
        "oriPrice": 298,
        "stockNum": 312,
        "dayOptions": [
          "30"
        ],
        "dataOptions": [
          "6"
        ]
      },
      {
        "prepaidCardId": 11237177,
        "realPrice": 161,
        "oriPrice": 358,
        "stockNum": 280,
        "dayOptions": [
          "30"
        ],
        "dataOptions": [
          "10"
        ]
      }
    ]
  },
  {
    "goodsId": "1021033",
    "goodsName": "法國通話上網卡",
    "totalSkus": 1,
    "totalCombos": 1,
    "variants": [
      {
        "prepaidCardId": 11237180,
        "realPrice": 76,
        "oriPrice": 188,
        "stockNum": 287,
        "dayOptions": [
          "15"
        ],
        "dataOptions": [
          "8"
        ]
      }
    ]
  },
  {
    "goodsId": "1021123",
    "goodsName": "美墨上網卡",
    "totalSkus": 1,
    "totalCombos": 3,
    "variants": [
      {
        "prepaidCardId": 11237385,
        "realPrice": 80,
        "oriPrice": 268,
        "stockNum": 234,
        "dayOptions": [
          "30",
          "60",
          "90"
        ],
        "dataOptions": [
          "25"
        ]
      }
    ]
  },
  {
    "goodsId": "1021124",
    "goodsName": "南美洲30日上網卡",
    "totalSkus": 1,
    "totalCombos": 1,
    "variants": [
      {
        "prepaidCardId": 11237386,
        "realPrice": 209,
        "oriPrice": 278,
        "stockNum": 486,
        "dayOptions": [
          "30"
        ],
        "dataOptions": [
          "3"
        ]
      }
    ]
  },
  {
    "goodsId": "1021191",
    "goodsName": "內地、香港及澳門365日上網卡",
    "totalSkus": 1,
    "totalCombos": 1,
    "variants": [
      {
        "prepaidCardId": 11237528,
        "realPrice": 211,
        "oriPrice": 368,
        "stockNum": 1256,
        "dayOptions": [
          "365"
        ],
        "dataOptions": [
          "36+9"
        ]
      }
    ]
  },
  {
    "goodsId": "1021295",
    "goodsName": "澳洲90日上網卡 (50GB)",
    "totalSkus": 1,
    "totalCombos": 1,
    "variants": [
      {
        "prepaidCardId": 11238509,
        "realPrice": 157,
        "oriPrice": 388,
        "stockNum": 250,
        "dayOptions": [
          "90"
        ],
        "dataOptions": [
          "51200"
        ]
      }
    ]
  },
  {
    "goodsId": "10200131",
    "goodsName": "巴基斯坦、哈薩克及指定中東多地上網卡",
    "totalSkus": 3,
    "totalCombos": 3,
    "variants": [
      {
        "prepaidCardId": 11238591,
        "realPrice": 538,
        "oriPrice": 538,
        "stockNum": 300,
        "dayOptions": [
          "30"
        ],
        "dataOptions": [
          "10240"
        ]
      },
      {
        "prepaidCardId": 11238587,
        "realPrice": 338,
        "oriPrice": 338,
        "stockNum": 50,
        "dayOptions": [
          "30"
        ],
        "dataOptions": [
          "4096"
        ]
      },
      {
        "prepaidCardId": 11238589,
        "realPrice": 438,
        "oriPrice": 438,
        "stockNum": 50,
        "dayOptions": [
          "30"
        ],
        "dataOptions": [
          "6144"
        ]
      }
    ]
  },
  {
    "goodsId": "10200137",
    "goodsName": "英法意等7國上網卡",
    "totalSkus": 1,
    "totalCombos": 4,
    "variants": [
      {
        "prepaidCardId": 11238614,
        "realPrice": 56,
        "oriPrice": 138,
        "stockNum": 141,
        "dayOptions": [
          "12",
          "180",
          "30",
          "90"
        ],
        "dataOptions": [
          "12288"
        ]
      }
    ]
  },
  {
    "goodsId": "10200148",
    "goodsName": "美墨上網卡",
    "totalSkus": 1,
    "totalCombos": 2,
    "variants": [
      {
        "prepaidCardId": 11238661,
        "realPrice": 208,
        "oriPrice": 338,
        "stockNum": 300,
        "dayOptions": [
          "60",
          "90"
        ],
        "dataOptions": [
          "51200"
        ]
      }
    ]
  }
]